rcon_host/__init__.py
rcon_host/log.py
rcon_host/rcon_host.py
rcon_host-0.1.dist-info/METADATA
rcon_host-0.1.dist-info/WHEEL
rcon_host-0.1.dist-info/top_level.txt
rcon_host-0.1.dist-info/RECORD
