Metadata-Version: 2.1
Name: rcon-host
Version: 0.1
Summary: The RCON-Host library allows you to accept user commands using the RCON protocol.
Home-page: https://github.com/local1ka/rcon-host.git
Author: local1ka
Author-email: alexarst@mail.ru
License: UNKNOWN
Project-URL: GitHub, https://github.com/local1ka/rcon-host.git
Keywords: rcon rcon_host rcon-host rcon_server rcon-server local1ka
Platform: UNKNOWN
Requires-Python: >=3.6
